<?xml version="1.0" encoding="UTF-8" ?>
<!DOCTYPE tiles-definitions PUBLIC "-//Apache Software Foundation//DTD Tiles Configuration 3.0//EN" "http://tiles.apache.org/dtds/tiles-config_3_0.dtd">


<tiles-definitions>

<!--  websocket -->
	<definition name="websocket"  template="/WEB-INF/jsp/websocket.jsp">
	</definition>
	<definition name="websocket2"  template="/WEB-INF/jsp/websocket2.jsp">
	</definition>
	<definition name="stock"  template="/WEB-INF/jsp/stock.jsp">
	</definition>
	


	<!-- TEMPLATES -->
	<definition name="defaultTemplate" template="/WEB-INF/jsp/template/template.jsp">
		<put-attribute name="navbar" value="/WEB-INF/jsp/template/navbar.jsp" />
		<put-attribute name="leftMenuContent" value="/WEB-INF/jsp/template/leftMenuContent.jsp" />
		<put-attribute name="eventsMainWindow" value="" />
		<put-attribute name="content" value="" />
		<put-attribute name="footer" value="/WEB-INF/jsp/template/footer.jsp" />
	</definition>
	<definition name="clearTemplate" template="/WEB-INF/jsp/template/clearTemplate.jsp">
		<put-attribute name="content" value="" />
	</definition>
	
	
	<!-- ACCOUNT -->
	<definition name="editAccount" extends="defaultTemplate">
		<put-attribute name="content" value="/WEB-INF/jsp/account/edit.jsp" />
	</definition>
	<definition name="login" extends="clearTemplate">
		<put-attribute name="content" value="/WEB-INF/jsp/account/login.jsp" />
	</definition>
	<definition name="password" extends="defaultTemplate">
		<put-attribute name="content" value="/WEB-INF/jsp/account/password.jsp" />
	</definition>
	<definition name="register" extends="clearTemplate">
		<put-attribute name="content" value="/WEB-INF/jsp/account/register.jsp" />
	</definition>
	<definition name="profile" extends="defaultTemplate">
		<put-attribute name="content" value="/WEB-INF/jsp/account/profile.jsp" />
	</definition>
	
	
	<!-- EVENT -->
	<definition name="create" extends="defaultTemplate">
		<put-attribute name="content" value="/WEB-INF/jsp/event/create.jsp" />
	</definition>
	<definition name="eventCreated" extends="defaultTemplate">
		<put-attribute name="content" value="/WEB-INF/jsp/event/created.jsp" />
	</definition>
	<definition name="details" extends="defaultTemplate">
		<put-attribute name="content" value="/WEB-INF/jsp/event/details.jsp" />
	</definition>
	<definition name="eventEdit" extends="defaultTemplate">
		<put-attribute name="content" value="/WEB-INF/jsp/event/edit.jsp" />
	</definition>
	<!-- organized -->
	<definition name="eventsInState" extends="defaultTemplate">
		<put-attribute name="eventsMainWindow" value="/WEB-INF/jsp/template/eventStatesMainWindow.jsp" />
		<put-attribute name="content" value="/WEB-INF/jsp/event/organized.jsp" />
	</definition>
	<definition name="eventsInStateByRole" extends="defaultTemplate">
		<put-attribute name="content" value="/WEB-INF/jsp/event/organized.jsp" />
	</definition>
	
	
	<!-- FRIEND -->
	<definition name="friends" extends="defaultTemplate">
		<put-attribute name="content" value="/WEB-INF/jsp/friend/friends.jsp" />
	</definition>
		<definition name="searchFriends" extends="defaultTemplate">
		<put-attribute name="content" value="/WEB-INF/jsp/friend/search.jsp" />
	</definition>

	
	<!-- GRAPHIC -->
	<definition name="graphic" extends="defaultTemplate">
		<put-attribute name="content" value="/WEB-INF/jsp/graphic/graphic.jsp" />
	</definition>
	<definition name="reserve" extends="defaultTemplate">
		<put-attribute name="content" value="/WEB-INF/jsp/graphic/reserve.jsp" />
	</definition>
	
	
	<!-- PLANNER -->
	<definition name="javaplanner"  template="/WEB-INF/jsp/planner/javaplanner.jsp" >
	</definition>


	<!-- HOME&HELP -->
	<definition name="home" extends="defaultTemplate">
		<put-attribute name="eventsMainWindow" value="/WEB-INF/jsp/template/eventStatesMainWindow.jsp" />
		<put-attribute name="content" value="/WEB-INF/jsp/home.jsp" />
	</definition>
		<definition name="help" extends="defaultTemplate">
		<put-attribute name="content" value="/WEB-INF/jsp/help.jsp" />
	</definition>
	

	<!-- ERRORS -->
	<definition name="error" template="/WEB-INF/jsp/errors/error404.jsp">
	</definition>


</tiles-definitions>


